README.rst
setup.py
ballpark_fixed/__init__.py
ballpark_fixed/notation.py
ballpark_fixed/shortcuts.py
ballpark_fixed/statistics.py
ballpark_fixed/tests.py
ballpark_fixed/utils.py
ballpark_fixed.egg-info/PKG-INFO
ballpark_fixed.egg-info/SOURCES.txt
ballpark_fixed.egg-info/dependency_links.txt
ballpark_fixed.egg-info/top_level.txt