Metadata-Version: 1.1
Name: ballpark-fixed
Version: 1.4.1
Summary: Better human-readable numbers. Forked and fixed from Stijn
Home-page: https://github.com/Endlesszombiez/python-ballpark
Author: Endlessz
Author-email: lckrep@protonmail.com
License: ISC
Keywords: human numbers format notation scientific engineering
Platform: UNKNOWN
Classifier: Development Status :: 4 - Beta
Classifier: Intended Audience :: Developers
Classifier: License :: OSI Approved :: ISC License (ISCL)
Classifier: Operating System :: OS Independent
Classifier: Topic :: Scientific/Engineering :: Information Analysis
Classifier: Topic :: Utilities
Classifier: Programming Language :: Python
Classifier: Programming Language :: Python :: 2
Classifier: Programming Language :: Python :: 2.7
Classifier: Programming Language :: Python :: 3
Classifier: Programming Language :: Python :: 3.4
Classifier: Programming Language :: Python :: 3.10
